<?xml version="1.0"?>
<opencv_storage>
<stage3>
  <maxWeakCount>8</maxWeakCount>
  <stageThreshold>-1.4838404655456543e+00</stageThreshold>
  <weakClassifiers>
    <_>
      <internalNodes>
        0 -1 87798 -5.1269878167659044e-04</internalNodes>
      <leafValues>
        5.3868192434310913e-01 -4.1685143113136292e-01</leafValues></_>
    <_>
      <internalNodes>
        0 -1 126486 -1.5021509025245905e-03</internalNodes>
      <leafValues>
        3.7103334069252014e-01 -5.2581727504730225e-01</leafValues></_>
    <_>
      <internalNodes>
        0 -1 7684 -4.0432281093671918e-04</internalNodes>
      <leafValues>
        5.8132553100585938e-01 -3.6894881725311279e-01</leafValues></_>
    <_>
      <internalNodes>
        0 -1 102318 -1.6129166760947555e-04</internalNodes>
      <leafValues>
        4.4139689207077026e-01 -4.1891148686408997e-01</leafValues></_>
    <_>
      <internalNodes>
        0 -1 75049 3.5500451922416687e-02</internalNodes>
      <leafValues>
        2.3738478124141693e-01 -7.3158878087997437e-01</leafValues></_>
    <_>
      <internalNodes>
        0 -1 101840 5.7483864948153496e-03</internalNodes>
      <leafValues>
        -7.6819354295730591e-01 2.4403588473796844e-01</leafValues></_>
    <_>
      <internalNodes>
        0 -1 127812 -7.6547887874767184e-04</internalNodes>
      <leafValues>
        3.8962206244468689e-01 -5.0654798746109009e-01</leafValues></_>
    <_>
      <internalNodes>
        0 -1 108264 8.0268047749996185e-03</internalNodes>
      <leafValues>
        2.7181595563888550e-01 -7.0375275611877441e-01</leafValues></_></weakClassifiers></stage3>
</opencv_storage>
